[
    {
        "group": "Young Avengers",
        "name": "Hawkeye "
    },
    {
        "group": "Young Avengers",
        "name": "Hulkling"
    },
    {
        "group": "Young Avengers",
        "name": "Iron Lad"
    },
    {
        "group": "Young Avengers",
        "name": "Kid Loki"
    },
    {
        "group": "Young Avengers",
        "name": "Marvel Boy"
    },
    {
        "group": "Young Avengers",
        "name": "Miss America"
    },
    {
        "group": "Young Avengers",
        "name": "Ms. Marvel"
    },
    {
        "group": "Young Avengers",
        "name": "She-Hulk"
    },
    {
        "group": "Young Avengers",
        "name": "Speed"
    },
    {
        "group": "Young Avengers",
        "name": "Stature"
    },
    {
        "group": "Young Avengers",
        "name": "Vision"
    },
    {
        "group": "Young Avengers",
        "name": "Wiccan"
    }
]